open_ksa/__init__.py
open_ksa/cli.py
open_ksa/config.py
open_ksa/download_file.py
open_ksa/download_helpers.py
open_ksa/downloader.py
open_ksa/get_dataset_resource.py
open_ksa/get_dataset_resources.py
open_ksa/get_org_resources.py
open_ksa/manifest.py
open_ksa/models.py
open_ksa/notebook.py
open_ksa/organizations.py
open_ksa/reader_adapters.py
open_ksa/ssl_adapter.py
open_ksa/tests/__init__.py
open_ksa/tests/test_get_dataset_resource.py
open_ksa/tests/test_organizations.py
open_ksa/tests/contract/test_browse_contract.py
open_ksa/tests/contract/test_cli_contract.py
open_ksa/tests/contract/test_download_api_contract.py
open_ksa/tests/contract/test_notebook_api_contract.py
open_ksa/tests/integration/test_cli_download_flow.py
open_ksa/tests/integration/test_notebook_quickstart.py
open_ksa/tests/integration/test_notebook_traversal.py
open_ksa/tests/integration/test_on_disk_prompt.py
open_ksa/tests/integration/test_streaming_sample.py
open_ksa/tests/unit/test_models_dataset.py
open_ksa/tests/unit/test_models_manifest.py
open_ksa/tests/unit/test_models_organization.py
open_ksa/tests/unit/test_models_resource.py
open_ksa/tests/unit/test_reader_adapter.py
open_ksa/tests/unit/test_reader_adapters_impl.py
open_ksa-0.2.0.dist-info/licenses/LICENSE
open_ksa-0.2.0.dist-info/METADATA
open_ksa-0.2.0.dist-info/WHEEL
open_ksa-0.2.0.dist-info/top_level.txt
open_ksa-0.2.0.dist-info/RECORD
