Metadata-Version: 2.4
Name: open_ksa
Version: 0.2.0
Summary: Commands to download datasets from the Open Data portal of the Kingdom of Saudi Arabia (KSA).
Author-email: Esteban Valencia <me@estebanvalencia.com>
Maintainer-email: Esteban Valencia <me@estebanvalencia.com>
License: MIT
Keywords: open data,KSA,datasets,API
Classifier: Development Status :: 4 - Beta
Classifier: Intended Audience :: Developers
Classifier: License :: OSI Approved :: MIT License
Classifier: Programming Language :: Python :: 3
Classifier: Programming Language :: Python :: 3.9
Classifier: Programming Language :: Python :: 3.10
Classifier: Programming Language :: Python :: 3.11
Classifier: Programming Language :: Python :: 3.12
Classifier: Topic :: Software Development :: Libraries :: Python Modules
Requires-Python: >=3.9.1
License-File: LICENSE
Requires-Dist: requests>=2.32.3
Requires-Dist: urllib3>=2.2.3
Requires-Dist: setuptools_scm>=8.0.0
Requires-Dist: tqdm>=4.0.0
Provides-Extra: dev
Requires-Dist: pytest>=7.0; extra == "dev"
Dynamic: license-file
